{
  "pools": [
    {
      "rolls": 1,
      "entries": [
        {
          "type": "minecraft:loot_table",
          "value": "just_plushies:plushie/pool/miscellaneous/common",
          "weight": 60
        },
        {
          "type": "minecraft:loot_table",
          "value": "just_plushies:plushie/pool/miscellaneous/uncommon",
          "weight": 28
        },
        {
          "type": "minecraft:loot_table",
          "value": "just_plushies:plushie/pool/miscellaneous/rare",
          "weight": 10
        },
        {
          "type": "minecraft:loot_table",
          "value": "just_plushies:plushie/pool/miscellaneous/epic",
          "weight": 2
        }
      ]
    }
  ]
}